{"_id":{"$oid":"5c14fdc0a29f9449d37e7556"},"﻿id":2,"category":"服饰","time":"11/29/2018 08:56:05"}
{"_id":{"$oid":"5c14fdc0a29f9449d37e7557"},"﻿id":3,"category":"鞋靴","time":"11/29/2018 08:56:05"}
{"_id":{"$oid":"5c14fdc0a29f9449d37e7558"},"﻿id":5,"category":"配饰","time":"11/29/2018 08:56:05"}
{"_id":{"$oid":"5c14fdc0a29f9449d37e7559"},"﻿id":6,"category":"妆品","time":"11/29/2018 08:56:05"}
{"_id":{"$oid":"5c14fdc0a29f9449d37e755a"},"﻿id":7,"category":"生活","time":"11/29/2018 08:56:05"}
{"_id":{"$oid":"5c14fdc0a29f9449d37e755b"},"﻿id":8,"category":"婴童","time":"11/29/2018 08:56:05"}
{"_id":{"$oid":"5c14fdc0a29f9449d37e755c"},"﻿id":4,"category":"腕表","time":"11/30/2018 12:43:13"}
{"_id":{"$oid":"5c14fdc0a29f9449d37e755d"},"﻿id":1,"category":"包袋","time":"11/29/2018 08:56:05"}
