{"_id":{"$oid":"5c14fd64a29f9449d37e7435"},"﻿id":2,"username":"Bob333","password":"123456","email":"haha@126.com","address":"上海","gender":"male","tel":"16522800754","time":"11/13/2018 19:45:55","status":"1"}
{"_id":{"$oid":"5c14fd64a29f9449d37e7436"},"﻿id":4,"username":"Lilly","password":"666666","email":"mary@123.com","address":"深圳","gender":"female","tel":"15280080007","time":"11/13/2018 22:14:34","status":"1"}
{"_id":{"$oid":"5c14fd64a29f9449d37e7437"},"﻿id":7,"username":"Yamy","password":"123456","email":"yamy@163.com","address":"杭州","gender":"male","tel":"15280070005","time":"11/13/2018 22:15:20","status":"0"}
{"_id":{"$oid":"5c14fd64a29f9449d37e7438"},"﻿id":8,"username":"Mary","password":"123456","email":"yes@163.com","address":"北京","gender":"female","tel":"15280090085","time":"11/13/2018 19:45:41","status":"1"}
{"_id":{"$oid":"5c14fd64a29f9449d37e7439"},"﻿id":9,"username":"Bob","password":"123456","email":"haha@126.com","address":"上海","gender":"male","tel":"16522800754","time":"11/13/2018 19:45:55","status":"1"}
{"_id":{"$oid":"5c14fd64a29f9449d37e743a"},"﻿id":1,"username":"Mary","password":"123456","email":"yes@163.com","address":"北京","gender":"female","tel":"15280090085","time":"11/13/2018 19:45:41","status":"1"}
{"_id":{"$oid":"5c14fd64a29f9449d37e743b"},"﻿id":11,"username":"Lilly","password":"666666","email":"mary@123.com","address":"深圳","gender":"female","tel":"15280080007","time":"11/13/2018 22:14:34","status":"1"}
{"_id":{"$oid":"5c14fd64a29f9449d37e743c"},"﻿id":10,"username":"Kate","password":"123456","email":"123@qq.com","address":"广州","gender":"female","tel":"15280090088","time":"11/13/2018 19:45:45","status":"1"}
{"_id":{"$oid":"5c14fd64a29f9449d37e743d"},"﻿id":3,"username":"Kate","password":"123456","email":"123@qq.com","address":"广州","gender":"female","tel":"15280090088","time":"11/13/2018 19:45:45","status":"1"}
{"_id":{"$oid":"5c14fd64a29f9449d37e743e"},"﻿id":14,"username":"Kate","password":"123456","email":"123@qq.com","address":"广州","gender":"female","tel":"15280090088","time":"11/13/2018 19:45:45","status":"1"}
{"_id":{"$oid":"5c14fd64a29f9449d37e743f"},"﻿id":13,"username":"Bob","password":"123456","email":"haha@126.com","address":"上海","gender":"male","tel":"16522800754","time":"11/13/2018 19:45:55","status":"1"}
{"_id":{"$oid":"5c14fd64a29f9449d37e7440"},"﻿id":15,"username":"Lilly","password":"666666","email":"mary@123.com","address":"深圳","gender":"female","tel":"15280080007","time":"11/13/2018 22:14:34","status":"1"}
{"_id":{"$oid":"5c14fd64a29f9449d37e7441"},"﻿id":16,"username":"Yamy","password":"123456","email":"yamy@163.com","address":"杭州","gender":"male","tel":"15280070005","time":"11/13/2018 22:15:20","status":"0"}
{"_id":{"$oid":"5c14fd64a29f9449d37e7442"},"﻿id":17,"username":"Mary","password":"123456","email":"yes@163.com","address":"北京","gender":"female","tel":"15280090085","time":"11/13/2018 19:45:41","status":"1"}
{"_id":{"$oid":"5c14fd64a29f9449d37e7443"},"﻿id":18,"username":"Bob","password":"123456","email":"haha@126.com","address":"上海","gender":"male","tel":"16522800754","time":"11/13/2018 19:45:55","status":"1"}
{"_id":{"$oid":"5c14fd64a29f9449d37e7444"},"﻿id":19,"username":"Kate","password":"123456","email":"123@qq.com","address":"广州","gender":"female","tel":"15280090088","time":"11/13/2018 19:45:45","status":"1"}
{"_id":{"$oid":"5c14fd64a29f9449d37e7445"},"﻿id":12,"username":"Yamy","password":"123456","email":"yamy@163.com","address":"杭州","gender":"male","tel":"15280070005","time":"11/13/2018 22:15:20","status":"0"}
{"_id":{"$oid":"5c14fd64a29f9449d37e7446"},"﻿id":22,"username":"Kate","password":"123456","email":"123@qq.com","address":"广州","gender":"female","tel":"15280090088","time":"11/13/2018 19:45:45","status":"1"}
{"_id":{"$oid":"5c14fd64a29f9449d37e7447"},"﻿id":20,"username":"Mary","password":"123456","email":"yes@163.com","address":"北京","gender":"female","tel":"15280090085","time":"11/13/2018 19:45:41","status":"1"}
{"_id":{"$oid":"5c14fd64a29f9449d37e7448"},"﻿id":21,"username":"Bob","password":"123456","email":"haha@126.com","address":"上海","gender":"male","tel":"16522800754","time":"11/13/2018 19:45:55","status":"1"}
{"_id":{"$oid":"5c14fd64a29f9449d37e7449"},"﻿id":23,"username":"Lilly","password":"666666","email":"mary@123.com","address":"深圳","gender":"female","tel":"15280080007","time":"11/13/2018 22:14:34","status":"1"}
{"_id":{"$oid":"5c14fd64a29f9449d37e744a"},"﻿id":24,"username":"Yamy","password":"123456","email":"yamy@163.com","address":"杭州","gender":"male","tel":"15280070005","time":"11/13/2018 22:15:20","status":"0"}
{"_id":{"$oid":"5c14fd64a29f9449d37e744b"},"﻿id":25,"username":"Mary","password":"123456","email":"yes@163.com","address":"北京","gender":"female","tel":"15280090085","time":"11/13/2018 19:45:41","status":"1"}
{"_id":{"$oid":"5c14fd64a29f9449d37e744c"},"﻿id":26,"username":"Bob","password":"123456","email":"haha@126.com","address":"上海","gender":"male","tel":"16522800754","time":"11/13/2018 19:45:55","status":"1"}
{"_id":{"$oid":"5c14fd64a29f9449d37e744d"},"﻿id":27,"username":"Kate","password":"123456","email":"123@qq.com","address":"广州","gender":"female","tel":"15280090088","time":"11/13/2018 19:45:45","status":"1"}
{"_id":{"$oid":"5c14fd64a29f9449d37e744e"},"﻿id":28,"username":"Lilly","password":"666666","email":"mary@123.com","address":"深圳","gender":"female","tel":"15280080007","time":"11/13/2018 22:14:34","status":"1"}
{"_id":{"$oid":"5c14fd64a29f9449d37e744f"},"﻿id":29,"username":"Yamy","password":"123456","email":"yamy@163.com","address":"杭州","gender":"male","tel":"15280070005","time":"11/13/2018 22:15:20","status":"0"}
{"_id":{"$oid":"5c14fd64a29f9449d37e7450"},"﻿id":30,"username":"Bob","password":"123456","email":"haha@126.com","address":"上海","gender":"male","tel":"16522800754","time":"11/13/2018 19:45:55","status":"1"}
{"_id":{"$oid":"5c14fd64a29f9449d37e7451"},"﻿id":32,"username":"Lilly","password":"666666","email":"mary@123.com","address":"深圳","gender":"female","tel":"15280080007","time":"11/13/2018 22:14:34","status":"1"}
{"_id":{"$oid":"5c14fd64a29f9449d37e7452"},"﻿id":31,"username":"Kate","password":"123456","email":"123@qq.com","address":"广州","gender":"female","tel":"15280090088","time":"11/13/2018 19:45:45","status":"1"}
{"_id":{"$oid":"5c14fd64a29f9449d37e7453"},"﻿id":33,"username":"Yamy","password":"123456","email":"yamy@163.com","address":"杭州","gender":"male","tel":"15280070005","time":"11/13/2018 22:15:20","status":"0"}
{"_id":{"$oid":"5c14fd64a29f9449d37e7454"},"﻿id":34,"username":"Mary","password":"123456","email":"yes@163.com","address":"北京","gender":"female","tel":"15280090085","time":"11/13/2018 19:45:41","status":"1"}
{"_id":{"$oid":"5c14fd64a29f9449d37e7455"},"﻿id":36,"username":"Kate","password":"123456","email":"123@qq.com","address":"广州","gender":"female","tel":"15280090088","time":"11/13/2018 19:45:45","status":"1"}
{"_id":{"$oid":"5c14fd64a29f9449d37e7456"},"﻿id":38,"username":"Kate","password":"123456","email":"123@qq.com","address":"广州","gender":"female","tel":"15280090088","time":"11/13/2018 19:45:45","status":"1"}
{"_id":{"$oid":"5c14fd64a29f9449d37e7457"},"﻿id":39,"username":"Lilly","password":"666666","email":"mary@123.com","address":"深圳","gender":"female","tel":"15280080007","time":"11/13/2018 22:14:34","status":"1"}
{"_id":{"$oid":"5c14fd64a29f9449d37e7458"},"﻿id":40,"username":"Yamy","password":"123456","email":"yamy@163.com","address":"杭州","gender":"male","tel":"15280070005","time":"11/13/2018 22:15:20","status":"0"}
{"_id":{"$oid":"5c14fd64a29f9449d37e7459"},"﻿id":41,"username":"Mary","password":"123456","email":"yes@163.com","address":"北京","gender":"female","tel":"15280090085","time":"11/13/2018 19:45:41","status":"1"}
{"_id":{"$oid":"5c14fd64a29f9449d37e745a"},"﻿id":42,"username":"Bob","password":"123456","email":"haha@126.com","address":"上海","gender":"male","tel":"16522800754","time":"11/13/2018 19:45:55","status":"1"}
{"_id":{"$oid":"5c14fd64a29f9449d37e745b"},"﻿id":43,"username":"Kate","password":"123456","email":"123@qq.com","address":"广州","gender":"female","tel":"15280090088","time":"11/13/2018 19:45:45","status":"1"}
{"_id":{"$oid":"5c14fd64a29f9449d37e745c"},"﻿id":37,"username":"Bob","password":"123456","email":"haha@126.com","address":"上海","gender":"male","tel":"16522800754","time":"11/13/2018 19:45:55","status":"1"}
{"_id":{"$oid":"5c14fd64a29f9449d37e745d"},"﻿id":35,"username":"Bob","password":"123456","email":"haha@126.com","address":"上海","gender":"male","tel":"16522800754","time":"11/13/2018 19:45:55","status":"1"}
{"_id":{"$oid":"5c14fd64a29f9449d37e745e"},"﻿id":44,"username":"Mary","password":"123456","email":"yes@163.com","address":"北京","gender":"female","tel":"15280090085","time":"11/13/2018 19:45:41","status":"1"}
{"_id":{"$oid":"5c14fd64a29f9449d37e745f"},"﻿id":48,"username":"Yamy","password":"123456","email":"yamy@163.com","address":"杭州","gender":"male","tel":"15280070005","time":"11/13/2018 22:15:20","status":"0"}
{"_id":{"$oid":"5c14fd64a29f9449d37e7460"},"﻿id":46,"username":"Kate","password":"123456","email":"123@qq.com","address":"广州","gender":"female","tel":"15280090088","time":"11/13/2018 19:45:45","status":"1"}
{"_id":{"$oid":"5c14fd64a29f9449d37e7462"},"﻿id":50,"username":"Bob","password":"123456","email":"haha@126.com","address":"上海","gender":"male","tel":"16522800754","time":"11/13/2018 19:45:55","status":"1"}
{"_id":{"$oid":"5c14fd64a29f9449d37e7463"},"﻿id":45,"username":"Bob","password":"123456","email":"haha@126.com","address":"上海","gender":"male","tel":"16522800754","time":"11/13/2018 19:45:55","status":"1"}
{"_id":{"$oid":"5c14fd64a29f9449d37e7464"},"﻿id":47,"username":"Lilly","password":"666666","email":"mary@123.com","address":"深圳","gender":"female","tel":"15280080007","time":"11/13/2018 22:14:34","status":"1"}
